{"User.3746f1d6-4d8f-415d-991c-dcf8b95582c2": {"id": "3746f1d6-4d8f-415d-991c-dcf8b95582c2", "created_at": "2023-11-10T16:23:05.483094", "updated_at": "2023-11-10T16:23:05.483132", "first_name": "Betty", "last_name": "Bar", "email": "airbnb@mail.com", "password": "root", "__class__": "User"}, "User.39ea2575-03a9-4298-8a72-826aab668822": {"id": "39ea2575-03a9-4298-8a72-826aab668822", "created_at": "2023-11-10T16:23:05.483919", "updated_at": "2023-11-10T16:23:05.483932", "first_name": "John", "email": "airbnb2@mail.com", "password": "root", "__class__": "User"}, "BaseModel.1ede84f1-e6b8-4e14-b1b1-1ede972bd7dc": {"id": "1ede84f1-e6b8-4e14-b1b1-1ede972bd7dc", "created_at": "2023-11-10T16:28:01.464024", "updated_at": "2023-11-10T16:28:01.464155", "__class__": "BaseModel"}, "User.3090d2d9-3357-4338-917e-3d5697fe6cbe": {"id": "3090d2d9-3357-4338-917e-3d5697fe6cbe", "created_at": "2023-11-10T16:28:20.007040", "updated_at": "2023-11-10T16:28:20.007062", "first_name": "Betty", "last_name": "Bar", "email": "airbnb@mail.com", "password": "root", "__class__": "User"}, "User.e63c01b1-ecc6-4c98-a119-0ea076c3c95d": {"id": "e63c01b1-ecc6-4c98-a119-0ea076c3c95d", "created_at": "2023-11-10T16:28:20.008377", "updated_at": "2023-11-10T16:28:20.008394", "first_name": "John", "email": "airbnb2@mail.com", "password": "root", "__class__": "User"}, "User.09ed9d78-00a6-434c-a8c1-3d5156fb8533": {"id": "09ed9d78-00a6-434c-a8c1-3d5156fb8533", "created_at": "2023-11-10T16:42:40.139478", "updated_at": "2023-11-10T16:42:40.139504", "__class__": "User"}, "User.5ed98355-acea-4752-9676-2a4647c34e3d": {"id": "5ed98355-acea-4752-9676-2a4647c34e3d", "created_at": "2023-11-10T16:44:16.311537", "updated_at": "2023-11-10T16:44:16.311558", "__class__": "User"}, "State.ddab7072-db9d-4077-968c-feafcb9fd711": {"id": "ddab7072-db9d-4077-968c-feafcb9fd711", "created_at": "2023-11-10T16:47:32.833405", "updated_at": "2023-11-10T16:47:32.833426", "name": "\"Rabat\"", "__class__": "State"}, "Place.406de858-7517-4374-9bca-426bd8ee06a1": {"id": "406de858-7517-4374-9bca-426bd8ee06a1", "created_at": "2023-11-10T16:48:32.182730", "updated_at": "2023-11-10T16:48:32.182828", "number_rooms": "5", "__class__": "Place"}}